{"title":"\ud83c\udf70\ucf00\uc774\ud06c\ub791 \ud30c\ub974\ud398\ud30c\ub294 \ub514\uc800\ud2b8 \uce74\ud398 \ube0c\uc774\ub85c\uadf8\ud83c\udf70 / \uc870\uc5d0 zoe","author_name":"Zoe\u0027s \uc870\uc5d0","author_url":"https://www.youtube.com/@zoe_one","type":"video","height":113,"width":200,"version":"1.0","provider_name":"YouTube","provider_url":"https://www.youtube.com/","thumbnail_height":360,"thumbnail_width":480,"thumbnail_url":"https://i.ytimg.com/vi/34yXJFpYzNo/hqdefault.jpg","html":"\u003ciframe width=\u0022200\u0022 height=\u0022113\u0022 src=\u0022https://www.youtube.com/embed/34yXJFpYzNo?feature=oembed\u0022 frameborder=\u00220\u0022 allow=\u0022accelerometer; autoplay; clipboard-write; encrypted-media; gyroscope; picture-in-picture; web-share\u0022 referrerpolicy=\u0022strict-origin-when-cross-origin\u0022 allowfullscreen title=\u0022\ud83c\udf70\ucf00\uc774\ud06c\ub791 \ud30c\ub974\ud398\ud30c\ub294 \ub514\uc800\ud2b8 \uce74\ud398 \ube0c\uc774\ub85c\uadf8\ud83c\udf70 / \uc870\uc5d0 zoe\u0022\u003e\u003c/iframe\u003e"}